libcellml/__init__.py
libcellml/_analyser.pyd
libcellml/_analyserequation.pyd
libcellml/_analyserequationast.pyd
libcellml/_analyserexternalvariable.pyd
libcellml/_analysermodel.pyd
libcellml/_analyservariable.pyd
libcellml/_annotator.pyd
libcellml/_component.pyd
libcellml/_componententity.pyd
libcellml/_entity.pyd
libcellml/_enums.pyd
libcellml/_generator.pyd
libcellml/_generatorprofile.pyd
libcellml/_importedentity.pyd
libcellml/_importer.pyd
libcellml/_importsource.pyd
libcellml/_issue.pyd
libcellml/_logger.pyd
libcellml/_model.pyd
libcellml/_namedentity.pyd
libcellml/_parentedentity.pyd
libcellml/_parser.pyd
libcellml/_printer.pyd
libcellml/_reset.pyd
libcellml/_strict.pyd
libcellml/_types.pyd
libcellml/_units.pyd
libcellml/_validator.pyd
libcellml/_variable.pyd
libcellml/_version.pyd
libcellml/analyser.py
libcellml/analyserequation.py
libcellml/analyserequationast.py
libcellml/analyserexternalvariable.py
libcellml/analysermodel.py
libcellml/analyservariable.py
libcellml/annotator.py
libcellml/component.py
libcellml/componententity.py
libcellml/entity.py
libcellml/enums.py
libcellml/generator.py
libcellml/generatorprofile.py
libcellml/importedentity.py
libcellml/importer.py
libcellml/importsource.py
libcellml/issue.py
libcellml/libcellml.dll
libcellml/logger.py
libcellml/model.py
libcellml/namedentity.py
libcellml/parentedentity.py
libcellml/parser.py
libcellml/printer.py
libcellml/reset.py
libcellml/strict.py
libcellml/types.py
libcellml/units.py
libcellml/validator.py
libcellml/variable.py
libcellml/version.py
libcellml-0.6.3.dist-info/METADATA
libcellml-0.6.3.dist-info/WHEEL
libcellml-0.6.3.dist-info/top_level.txt
libcellml-0.6.3.dist-info/RECORD
